cfa/__init__.py
cfa/cli.py
cfa/commands/ICommand.py
cfa/commands/__init__.py
cfa/commands/command_builder.py
cfa/commands/impl/__init__.py
cfa/commands/impl/dependency_installer.py
cfa/commands/impl/dir_creator.py
cfa/commands/impl/git_clone.py
cfa/config/__init__.py
cfa/helpers/__init__.py
cfa/helpers/logger.py
create_fastapi-0.0.11.dist-info/METADATA
create_fastapi-0.0.11.dist-info/WHEEL
create_fastapi-0.0.11.dist-info/entry_points.txt
create_fastapi-0.0.11.dist-info/licenses/LICENSE
create_fastapi-0.0.11.dist-info/RECORD
