Metadata-Version: 2.1
Name: create-fastapi
Version: 0.0.11
Summary: create-fastapi-app
Project-URL: Homepage, https://github.com/shaharluftig/create-fastapi-app
Author-email: Shahar Luftig <shaharluftig@gmail.com>
License:                                  Apache License
License-File: LICENSE
Keywords: backend,create-app,create-fastapi-app,create-fatapi,fastapi
Classifier: Intended Audience :: Science/Research
Classifier: Operating System :: OS Independent
Classifier: Programming Language :: Python
Classifier: Programming Language :: Python :: 3
Classifier: Programming Language :: Python :: 3 :: Only
Classifier: Programming Language :: Python :: 3.7
Classifier: Programming Language :: Python :: 3.8
Classifier: Programming Language :: Python :: 3.9
Classifier: Programming Language :: Python :: 3.10
Classifier: Programming Language :: Python :: 3.11
Classifier: Topic :: Scientific/Engineering
Requires-Python: >=3.7
Requires-Dist: gitpython~=3.1.32
Requires-Dist: typer~=0.9.0
Requires-Dist: virtualenv~=20.24.1
